{
    "occurrence_over_time": [
        [
            "Films of the 1920s", 
            0, 
            0.0, 
            60
        ], 
        [
            "Films of the 1930s", 
            0, 
            0.0, 
            91
        ], 
        [
            "Films of the 1940s", 
            0, 
            0.0, 
            111
        ], 
        [
            "Films of the 1950s", 
            0, 
            0.0, 
            176
        ], 
        [
            "Films of the 1960s", 
            0, 
            0.0, 
            225
        ], 
        [
            "Films of the 1970s", 
            0, 
            0.0, 
            302
        ], 
        [
            "Films of the 1980s", 
            4, 
            0.0068143100511073255, 
            587
        ], 
        [
            "Films of the 1990s", 
            9, 
            0.010169491525423728, 
            885
        ], 
        [
            "Films of the 2000s", 
            3, 
            0.005272407732864675, 
            569
        ], 
        [
            "Films of the 2010s", 
            0, 
            0.0, 
            646
        ]
    ], 
    "description": "The diametric opposite of the Open Minded Parent is the Education Mama, a mother (and it's usually a mother) who is obsessed with her children's education and pushes them to succeed academically, no matter the cost. She will shell out thousands of dollars to send her kids to private school or move to another town with good schools, and her kids will be forced to surrender their social lives in the pursuit of good grades. And God help her kids if any of them gets anything less than an A. This trope is especially pervasive in East Asian families (due to the pervading Confucian tradition placing a heavy emphasis on education and due to the extremely cutthroat education systems found in Asian countries), to the point where it's become a stereotype that all Asian parents are like this. Such parents have been given the name \"Tiger Moms.\"\nContrast: Parental Abandonment, Open Minded Parent. Compare: Jewish Mother and My Beloved Smother. Can turn your child into a \"Well Done, Son\" Guy if all goes according to plan. If it goes pear-shaped, it can lead to a You Are Grounded moment, or worse still, teen angst or teen rebellion. In the worst cases, particularly in East Asia, the end result is attempted suicide, the Hikikomori, or even snap violence against the parents.\nThe Stage Mom is when this trope is applied to performing arts instead of academics. Jock Dad, Nerd Son is when this trope is applied to sports.\nNot to be confused with Cooking Mama.\n\nExamples", 
    "gender": "f", 
    "adjs": [
        "diametric", 
        "private", 
        "good", 
        "social", 
        "good"
    ], 
    "adjectives": [
        [
            "asian", 
            2, 
            11.471557190748317, 
            1.0, 
            [
                "EducationMama", 
                "YamatoNadeshiko", 
                "AsianBabymama", 
                "TheChiefsDaughter", 
                "DragonLady", 
                "WomenDrivers", 
                "Samurai", 
                "HookerWithAHeartOfGold", 
                "Bishonen", 
                "PrettyBoy", 
                "AsianHookerStereotype", 
                "AsianAirhead"
            ]
        ], 
        [
            "cutthroat", 
            1, 
            10.530773691358384, 
            0.9179899046182968, 
            [
                "EducationMama"
            ]
        ], 
        [
            "diametric", 
            1, 
            10.530773691358384, 
            0.9179899046182968, 
            [
                "EducationMama"
            ]
        ], 
        [
            "pear-shaped", 
            1, 
            10.530773691358384, 
            0.9179899046182968, 
            [
                "EducationMama"
            ]
        ], 
        [
            "pervasive", 
            1, 
            9.486866121696911, 
            0.8269902650485814, 
            [
                "MissKitty", 
                "EducationMama"
            ]
        ], 
        [
            "private", 
            1, 
            7.042505713496949, 
            0.6139101777025224, 
            [
                "UnluckyEveryDude", 
                "GoGetterGirl", 
                "DadTheVeteran", 
                "IronLady", 
                "MataHari", 
                "DrillSergeantNasty", 
                "ShamelessFanserviceGirl", 
                "EducationMama"
            ]
        ], 
        [
            "jewish", 
            1, 
            6.12950509278235, 
            0.5343219748514811, 
            [
                "EducationMama", 
                "ShiksaGoddess", 
                "JewishAmericanPrincess", 
                "EarthMother", 
                "NiceJewishBoy", 
                "JewishMother"
            ]
        ], 
        [
            "heavy", 
            1, 
            5.8582713851381865, 
            0.5106779565953624, 
            [
                "LittleMissAlmighty", 
                "ButchLesbian", 
                "TheChick", 
                "TheBear", 
                "ChildSoldiers", 
                "Beastess", 
                "BlondeRepublicanSexKitten", 
                "SculleryMaid", 
                "FarmersDaughter", 
                "NaughtyNurseOutfit", 
                "EducationMama", 
                "JeanneDArchetype", 
                "AsianHookerStereotype", 
                "FiremenAreHot", 
                "Ojou"
            ]
        ], 
        [
            "good", 
            2, 
            4.988148144455737, 
            0.4348274660112075, 
            [
                "OutdoorsyGal", 
                "ChildSoldiers", 
                "BeardOfBarbarism", 
                "AdrenalineMakeover", 
                "KickingAssInAllHerFinery", 
                "LovelyAssistant", 
                "CatholicSchoolGirlsRule", 
                "DrillSergeantNasty", 
                "TomboyPrincess", 
                "GIRL", 
                "EducationMama", 
                "DisguisedInDrag", 
                "KnightInShiningArmor", 
                "SpiritedYoungLady", 
                "ManInAKilt", 
                "AgentPeacock", 
                "MagicalGirlfriend", 
                "HuskyRusskie", 
                "TheGoodKing", 
                "TheLoinsSleepTonight", 
                "TheEvilPrince", 
                "TomboyWithAGirlyStreak", 
                "HeroicSeductress", 
                "ManInWhite", 
                "BathingBeauty", 
                "HandyMan", 
                "EverythingsBetterWithPrincesses", 
                "MilesGloriosus", 
                "DirtyCoward", 
                "NeutralFemale", 
                "StoutStrength", 
                "SpicyLatina", 
                "MyBelovedSmother", 
                "DirtyHarriet", 
                "NubileSavage", 
                "KavorkaMan", 
                "BlackBossLady", 
                "FatSweatySouthernerInAWhiteSuit", 
                "ProperLady", 
                "DarkMagicalGirl", 
                "WizardBeard", 
                "MadScientistsBeautifulDaughter", 
                "DumbMuscle", 
                "DirtyOldMan", 
                "HouseHusband", 
                "TheCheerleader", 
                "GodSaveUsFromTheQueen", 
                "BeardOfEvil", 
                "AsianAirhead", 
                "LadyInRed", 
                "HighClassCallGirl", 
                "GentlemanWizard", 
                "SeeminglyWholesomeFiftiesGirl", 
                "MagicIdolSinger", 
                "OfficerAndAGentleman", 
                "BeautifulAllAlong", 
                "BrokenBird", 
                "SassyBlackWoman", 
                "TheWisePrince", 
                "GymBunny", 
                "PerkyFemaleMinion", 
                "CoolOldLady", 
                "UncannyValleyGirl", 
                "StageMom", 
                "GoodBadGirl", 
                "WinterRoyalLady", 
                "LawmanGoneBad", 
                "LadyMacBeth", 
                "TheVamp", 
                "MadonnaWhoreComplex", 
                "TheBaroness", 
                "GamblerGroupies", 
                "HotScientist", 
                "PrincessClassic", 
                "HardDrinkingPartyGirl", 
                "SeashellBra", 
                "BaldBlackLeaderGuy", 
                "TakingTheVeil", 
                "GentlemanThief", 
                "ClassyCatBurglar", 
                "GirlNextDoor", 
                "DecoyDamsel", 
                "QuintessentialBritishGentleman", 
                "HookerWithAHeartOfGold", 
                "TheOphelia", 
                "Hobos", 
                "CrusadingWidower", 
                "TheButcher", 
                "AccidentalPornomancer", 
                "TheDandy", 
                "VainSorceress", 
                "BigManOnCampus", 
                "MachoMasochism", 
                "GoodGirlGoneBad", 
                "HotScoop", 
                "TheMuse", 
                "SwingLowSweetHarriet", 
                "BattleaxeNurse", 
                "HighSchoolHustler", 
                "LightFeminineAndDarkFeminine", 
                "MaidenAunt", 
                "YamatoNadeshiko", 
                "TheLadysFavour", 
                "FemmeFatale", 
                "HighHeelFaceTurn", 
                "CampGay", 
                "BlondeRepublicanSexKitten", 
                "MonogenderMonsters", 
                "ShelteredAristocrat", 
                "TheGambler", 
                "StatuesqueStunner", 
                "NobleMaleRoguishMale", 
                "PregnantHostage", 
                "SoapBoxSadie", 
                "Streetwalker", 
                "ChivalrousPervert", 
                "GrannyClassic", 
                "MorallyBankruptBanker", 
                "ValleyGirl", 
                "MataHari", 
                "WorldsMostBeautifulWoman", 
                "GrumpyOldMan", 
                "DefectingForLove", 
                "CuteSportsClubManager", 
                "DaddysLittleVillain", 
                "WickedWitch", 
                "RebelPrince", 
                "GrandeDame", 
                "MysteriousWaif", 
                "StumblingUponTheLostWizard", 
                "DarkActionGirl", 
                "BastardBastard", 
                "ButterFace", 
                "AbsentMindedProfessor", 
                "JewishMother", 
                "DamselInDistress"
            ]
        ], 
        [
            "social", 
            1, 
            4.0491857615653535, 
            0.35297612122188404, 
            [
                "Socialite", 
                "RichBitch", 
                "PrincelyYoungMan", 
                "MysticalWaif", 
                "LawmanGoneBad", 
                "EmotionlessGirl", 
                "Bridezilla", 
                "EducationMama", 
                "MadonnaWhoreComplex", 
                "GoGetterGirl", 
                "CampStraight", 
                "GirlOfTheWeek", 
                "AlphaBitch", 
                "LadyInWaiting", 
                "BasementDweller", 
                "GentlemanThief", 
                "NoWomansLand", 
                "MissKitty", 
                "GirlNextDoor", 
                "Kawaiiko", 
                "Samurai", 
                "OfficerAndAGentleman", 
                "GirlishPigtails", 
                "GrandeDame", 
                "AsianBabymama", 
                "HairyGirl", 
                "BarbaricBully", 
                "RebelliousPrincess", 
                "TheOneGuy", 
                "SissyVillain", 
                "ConceiveAndKill", 
                "TheChick"
            ]
        ]
    ], 
    "image_url": "assets/data/tropes/images/EducationMama.png", 
    "similar": [
        {
            "count": 2, 
            "related_trope": "SweaterGirl", 
            "trope": "EducationMama", 
            "films": [
                "Election", 
                "EmpireRecords"
            ]
        }, 
        {
            "count": 2, 
            "related_trope": "TeamMom", 
            "trope": "EducationMama", 
            "films": [
                "CampNowhere", 
                "LittleWomen"
            ]
        }, 
        {
            "count": 2, 
            "related_trope": "GoodBadGirl", 
            "trope": "EducationMama", 
            "films": [
                "TheBreakfastClub", 
                "EmpireRecords"
            ]
        }, 
        {
            "count": 1, 
            "related_trope": "GossipyHens", 
            "trope": "EducationMama", 
            "films": [
                "LittleWomen"
            ]
        }, 
        {
            "count": 1, 
            "related_trope": "StageMom", 
            "trope": "EducationMama", 
            "films": [
                "TheBreakfastClub"
            ]
        }, 
        {
            "count": 1, 
            "related_trope": "FilleFatale", 
            "trope": "EducationMama", 
            "films": [
                "Election"
            ]
        }, 
        {
            "count": 1, 
            "related_trope": "NakedShotaroBoy", 
            "trope": "EducationMama", 
            "films": [
                "DragonBall"
            ]
        }, 
        {
            "count": 1, 
            "related_trope": "PlayboyBunny", 
            "trope": "EducationMama", 
            "films": [
                "DragonBall"
            ]
        }, 
        {
            "count": 1, 
            "related_trope": "IllGirl", 
            "trope": "EducationMama", 
            "films": [
                "LittleWomen"
            ]
        }
    ], 
    "id": "EducationMama", 
    "name": "Education Mama"
}