{
    "occurrence_over_time": [
        [
            "Films of the 1920s", 
            0, 
            0.0, 
            60
        ], 
        [
            "Films of the 1930s", 
            0, 
            0.0, 
            91
        ], 
        [
            "Films of the 1940s", 
            0, 
            0.0, 
            111
        ], 
        [
            "Films of the 1950s", 
            1, 
            0.005681818181818182, 
            176
        ], 
        [
            "Films of the 1960s", 
            2, 
            0.008888888888888889, 
            225
        ], 
        [
            "Films of the 1970s", 
            5, 
            0.016556291390728478, 
            302
        ], 
        [
            "Films of the 1980s", 
            5, 
            0.008517887563884156, 
            587
        ], 
        [
            "Films of the 1990s", 
            11, 
            0.012429378531073447, 
            885
        ], 
        [
            "Films of the 2000s", 
            8, 
            0.014059753954305799, 
            569
        ], 
        [
            "Films of the 2010s", 
            13, 
            0.020123839009287926, 
            646
        ]
    ], 
    "description": "A Non Action Guy is a male who is not heavily endowed with a certain quality that's expected of males in shows; usually courage or combat ability. He's usually a sidekick; often to the Action Girl (or Action Girlfriend), or sometimes to an entire Five-Man Band. Expect him to need occasional rescuing. This combo has the added danger of the audience seeing him as The Chick, a role that can de-masculinize him (to male viewers) or just make him annoying (to all viewers).\nThe Non Action Guy seems much more likely to be played for comedy than the traditional female version of The Chick as while women are not expected to kick ass (and thus those that do are exceptional) men often are and so a Non Action Guy's lack of ability is written as something to laugh at.\nOften he'll either grow into a more action-oriented role, become ignored, or become the Butt Monkey as punishment for his failure at masculinity. A common, more acceptable practice is to put him on the Mission Control, where he can be of actual help without having to use any sort of action skill.\nThe preponderance of this can vary from fandom to fandom, though the fans might have a point depending on how the character's written. Trying to masculinate him can sometimes turn the Action Girl into a Faux Action Girl if done improperly. This is especially likely if the writers attempt to combine Rescue Romance with All Up To You... again... and again... (haven't these morons ever heard of the Battle Couple?!) You can even see tropers putting little 'Actually, this is why X character is really a badass' statements below some examples, as if it's impossible to be a badass and a Non Action Guy at the same time.\nExpect Fix Fics to be written where his character is changed to fit expectations as a Canon Sue. If he's the protagonist, then he's likely an Action Survivor. If he's the Villain, he's likely a Non-Action Big Bad. Compare Unfazed Everyman.\n\nExamples", 
    "gender": "m", 
    "adjs": [
        "certain", 
        "entire", 
        "occasional", 
        "comedy", 
        "traditional"
    ], 
    "adjectives": [
        [
            "exceptional", 
            1, 
            10.530773691358384, 
            1.0, 
            [
                "NonActionGuy"
            ]
        ], 
        [
            "action-oriented", 
            1, 
            8.809858692382944, 
            0.8365822826116154, 
            [
                "NonActionGuy", 
                "MagicalGirlfriend", 
                "AffirmativeActionGirl"
            ]
        ], 
        [
            "comedy", 
            1, 
            7.906982778672999, 
            0.7508453804454573, 
            [
                "NonActionGuy", 
                "StoutStrength", 
                "ButterFace", 
                "CrazyJealousGuy", 
                "TheLoinsSleepTonight"
            ]
        ], 
        [
            "impossible", 
            1, 
            7.042505713496949, 
            0.6687548246598511, 
            [
                "MachoCamp", 
                "GrandeDame", 
                "FemmeFatale", 
                "RichBitch", 
                "RightThroughHisPants", 
                "NonActionGuy", 
                "WickedWitch", 
                "BiggerIsBetterInBed"
            ]
        ], 
        [
            "entire", 
            1, 
            6.624666732723531, 
            0.6290769251037815, 
            [
                "BadassGrandpa", 
                "AmazonBrigade", 
                "DaddysGirl", 
                "NonActionGuy", 
                "Samurai", 
                "OfficeLady", 
                "ManInAKilt", 
                "MarySue", 
                "EstrogenBrigade", 
                "UncannyValleyGirl"
            ]
        ], 
        [
            "occasional", 
            1, 
            6.624666732723531, 
            0.6290769251037815, 
            [
                "JunglePrincess", 
                "MagicalGirlWarrior", 
                "PluckyOfficeGirl", 
                "CrazyCatLady", 
                "NonActionGuy", 
                "BlackWidow", 
                "TheCasanova", 
                "DirtyOldWoman", 
                "JewishMother", 
                "MartyStu"
            ]
        ], 
        [
            "acceptable", 
            1, 
            5.409349601380476, 
            0.51367067225264, 
            [
                "DisposableSexWorker", 
                "GlamorousWartimeSinger", 
                "BastardGirlfriend", 
                "NEET", 
                "SweaterGirl", 
                "TheHighQueen", 
                "GirlOfTheWeek", 
                "BlondGuysAreEvil", 
                "MartyStu", 
                "NonActionGuy", 
                "HotScoop", 
                "ProperLady", 
                "FemininityFailure", 
                "TheFlapper", 
                "TheGeneralissimo", 
                "StandardFiftiesFather", 
                "MommasBoy", 
                "LesbianJock", 
                "BasementDweller"
            ]
        ], 
        [
            "traditional", 
            1, 
            4.3069414728697275, 
            0.40898623397481515, 
            [
                "YamatoNadeshiko", 
                "HotWitch", 
                "MadScientistsBeautifulDaughter", 
                "TomBoyAndGirlyGirl", 
                "BoyBand", 
                "TomboyPrincess", 
                "Fundoshi", 
                "DoggedNiceGuy", 
                "DistressedDude", 
                "BlondeRepublicanSexKitten", 
                "BeardOfEvil", 
                "OldMaid", 
                "ManInAKilt", 
                "FeminineWomenCanCook", 
                "PassionateSportsGirl", 
                "NaginatasAreFeminine", 
                "CrazyCatLady", 
                "GracefulLadiesLikePurple", 
                "NonActionGuy", 
                "OneeSama", 
                "WomanInWhite", 
                "SweaterGirl", 
                "Fratbro", 
                "SenseiChan", 
                "ThePatriarch", 
                "EvilMatriarch", 
                "HouseWife", 
                "HotGypsyWoman", 
                "DamselOutOfDistress"
            ]
        ], 
        [
            "little", 
            1, 
            4.001769269797113, 
            0.3800071473457823, 
            [
                "OverprotectiveDad", 
                "LittleOldLadyInvestigates", 
                "GlamorousSingleMother", 
                "LittleRedFightingHood", 
                "BastardBoyfriend", 
                "DirtyOldMan", 
                "FarmersDaughter", 
                "TheCharmer", 
                "MagicalSeventhSon", 
                "UnluckyEveryDude", 
                "LittleSisterHeroine", 
                "SexistUsedCarSalesman", 
                "TheSlacker", 
                "MaidenAunt", 
                "WomanScorned", 
                "TheCutie", 
                "BasementDweller", 
                "PrincessPhase", 
                "ClassyCatBurglar", 
                "BespectacledBastardBoyfriend", 
                "QuintessentialBritishGentleman", 
                "NonActionGuy", 
                "BaitAndSwitchLesbians", 
                "BeautifulAllAlong", 
                "LittleMissConArtist", 
                "Tomboy", 
                "DirtyHarriet", 
                "FragileFlower", 
                "BrattyTeenageDaughter", 
                "FavorsForTheSexy", 
                "MysticalWaif", 
                "DarkActionGirl", 
                "SpoiledSweet", 
                "SwingLowSweetHarriet", 
                "Bishonen", 
                "LittleGirlsKickShins"
            ]
        ], 
        [
            "actual", 
            1, 
            3.5137909207904476, 
            0.3336688284996463, 
            [
                "MrsRobinson", 
                "AmazonChaser", 
                "ChildSoldiers", 
                "GranolaGirl", 
                "FrenchMaid", 
                "HugeSchoolgirl", 
                "HumanoidFemaleAnimal", 
                "WinterRoyalLady", 
                "DrillSergeantNasty", 
                "HouseHusband", 
                "GIRL", 
                "HeManWomanHater", 
                "TheVamp", 
                "Ojou", 
                "TheBear", 
                "GirlOfTheWeek", 
                "BaitAndSwitchLesbians", 
                "Dominatrix", 
                "SouthernGentleman", 
                "FauxActionGirl", 
                "TheGambler", 
                "TheGoodKing", 
                "BattleButler", 
                "GentlemanThief", 
                "Streetwalker", 
                "EmotionlessGirl", 
                "ClassyCatBurglar", 
                "UselessBoyfriend", 
                "GrannyClassic", 
                "StageMom", 
                "NaughtyNurseOutfit", 
                "NonActionGuy", 
                "Samurai", 
                "SensitiveGuyAndManlyMan", 
                "MilesGloriosus", 
                "OfficerAndAGentleman", 
                "FilleFatale", 
                "PerkyGoth", 
                "YaoiGuys", 
                "IdolSinger", 
                "RebelliousPrincess", 
                "TheOneGuy", 
                "FatSweatySouthernerInAWhiteSuit", 
                "LipstickLesbian", 
                "SingleMomStripper", 
                "LittleMissBadass", 
                "FanserviceExtra", 
                "LadyOfWar", 
                "BiggerIsBetterInBed"
            ]
        ], 
        [
            "certain", 
            1, 
            3.377286725515399, 
            0.3207064195375142, 
            [
                "YamatoNadeshiko", 
                "Fangirl", 
                "ChildSoldiers", 
                "TheEvilPrince", 
                "PrincelyYoungMan", 
                "GoodBadGirl", 
                "DirtyOldMan", 
                "MistressAndServantBoy", 
                "TheTease", 
                "EmotionlessGirl", 
                "TheVamp", 
                "PrettyBoy", 
                "FinalGirl", 
                "FeminineWomenCanCook", 
                "GoGetterGirl", 
                "SpiritedYoungLady", 
                "BashBrothers", 
                "TheFightingNarcissist", 
                "BeardOfEvil", 
                "ShelteredAristocrat", 
                "AgentPeacock", 
                "OldMaid", 
                "GentlemanThief", 
                "LesbianCop", 
                "JerkJock", 
                "ClassyCatBurglar", 
                "MissKitty", 
                "AcceptableFeminineGoalsAndTraits", 
                "ButchLesbian", 
                "InnocentFanserviceGirl", 
                "NonActionGuy", 
                "Samurai", 
                "DisposableSexWorker", 
                "SensitiveGuyAndManlyMan", 
                "GirlsLoveStuffedAnimals", 
                "HotWitch", 
                "DirtyCoward", 
                "EstrogenBrigade", 
                "DaddysLittleVillain", 
                "LesbianJock", 
                "YaoiGuys", 
                "ManlyGay", 
                "LeatherMan", 
                "IronLady", 
                "WomenDrivers", 
                "ShirtlessScene", 
                "SissyVillain", 
                "WomanInBlack", 
                "DumbassTeenageSon", 
                "LadyOfWar", 
                "GenderInvertedTrope"
            ]
        ], 
        [
            "same", 
            1, 
            2.02812607312495, 
            0.192590414775435, 
            [
                "OverprotectiveDad", 
                "ChildSoldiers", 
                "BeardOfBarbarism", 
                "Hobos", 
                "CatholicSchoolGirlsRule", 
                "DrillSergeantNasty", 
                "TheBear", 
                "SpiritedYoungLady", 
                "TheChiefsDaughter", 
                "HandsomeDevil", 
                "TeamMom", 
                "AlphaBitch", 
                "TheCasanova", 
                "BigBeautifulMan", 
                "HeroicSeductress", 
                "PoliticallyActivePrincess", 
                "ArabOilSheikh", 
                "UselessBoyfriend", 
                "EverythingsBetterWithPrincesses", 
                "DirtyCoward", 
                "TheIngenue", 
                "SpicyLatina", 
                "MyBelovedSmother", 
                "Tomboy", 
                "GayBravado", 
                "TheUglyGuysHotDaughter", 
                "HouseWife", 
                "WomenDrivers", 
                "FatSweatySouthernerInAWhiteSuit", 
                "Jailbait", 
                "MamaBear", 
                "GossipyHens", 
                "HugeSchoolgirl", 
                "AmazonianBeauty", 
                "TomBoyAndGirlyGirl", 
                "HouseHusband", 
                "SchoolgirlLesbians", 
                "UnluckyEveryDude", 
                "TheCheerleader", 
                "AsianAirhead", 
                "LipstickLesbian", 
                "MountainMan", 
                "CoolOldGuy", 
                "PassionateSportsGirl", 
                "DisposableSexWorker", 
                "FilleFatale", 
                "HelloNurse", 
                "ThePatriarch", 
                "ManlyGay", 
                "SexySecretary", 
                "MysticalWaif", 
                "EffeminateMisogynisticGuy", 
                "ScaryBlackMan", 
                "PluckyOfficeGirl", 
                "ALadyOnEachArm", 
                "CoolBigSis", 
                "TheBaroness", 
                "GagPenis", 
                "BashBrothers", 
                "Joshikousei", 
                "TheFlapper", 
                "SeashellBra", 
                "BaldBlackLeaderGuy", 
                "QuicklyDemotedWoman", 
                "JunglePrincess", 
                "PrinceCharmless", 
                "GirlNextDoor", 
                "MataHari", 
                "NonActionGuy", 
                "TheOphelia", 
                "LovelyAssistant", 
                "DistressedDude", 
                "AccidentalPornomancer", 
                "TheDandy", 
                "VainSorceress", 
                "CasanovaWannabe", 
                "MsFanservice", 
                "TheMuse", 
                "HotGypsyWoman", 
                "AnimeChineseGirl", 
                "HighHeelFaceTurn", 
                "DoggedNiceGuy", 
                "GoGetterGirl", 
                "NeverASelfMadeWoman", 
                "TheHecateSisters", 
                "FauxActionGirl", 
                "MonogenderMonsters", 
                "JeanneDArchetype", 
                "FeminineWomenCanCook", 
                "MartyStu", 
                "GamerChick", 
                "Fratbro", 
                "DefectingForLove", 
                "DaddysLittleVillain", 
                "LittleMissConArtist", 
                "CockFight", 
                "HotScientist", 
                "LesbianJock", 
                "ChickMagnet", 
                "AsianBabymama", 
                "LeatherMan", 
                "DragonLady", 
                "MisterSeahorse", 
                "TheOneGuy", 
                "JewishMother"
            ]
        ]
    ], 
    "image_url": "assets/data/tropes/images/NonActionGuy.jpg", 
    "similar": [
        {
            "count": 5, 
            "related_trope": "TheChick", 
            "trope": "NonActionGuy", 
            "films": [
                "Turbo", 
                "KungFuPanda", 
                "Predators", 
                "LemonadeMouth", 
                "Lawless"
            ]
        }, 
        {
            "count": 4, 
            "related_trope": "SissyVillain", 
            "trope": "NonActionGuy", 
            "films": [
                "Pocahontas", 
                "LupinIIIThePursuitOfHarimaosTreasure", 
                "Futurama", 
                "HeavyMetal"
            ]
        }, 
        {
            "count": 3, 
            "related_trope": "SharpDressedMan", 
            "trope": "NonActionGuy", 
            "films": [
                "TheGodfather", 
                "ActOfValor", 
                "HeavyRain"
            ]
        }, 
        {
            "count": 3, 
            "related_trope": "OverprotectiveDad", 
            "trope": "NonActionGuy", 
            "films": [
                "MontyPythonAndTheHolyGrail", 
                "LemonadeMouth", 
                "PhineasAndFerbTheMovieAcrossThe2ndDimension"
            ]
        }, 
        {
            "count": 3, 
            "related_trope": "StraightGay", 
            "trope": "NonActionGuy", 
            "films": [
                "TheGodfather", 
                "Futurama", 
                "MortalInstruments"
            ]
        }, 
        {
            "count": 3, 
            "related_trope": "TomBoyAndGirlyGirl", 
            "trope": "NonActionGuy", 
            "films": [
                "Bandidas", 
                "MortalInstruments", 
                "Hellboy"
            ]
        }, 
        {
            "count": 2, 
            "related_trope": "TheSquadette", 
            "trope": "NonActionGuy", 
            "films": [
                "Predators", 
                "StreetsOfFire"
            ]
        }, 
        {
            "count": 2, 
            "related_trope": "TheVamp", 
            "trope": "NonActionGuy", 
            "films": [
                "MontyPythonAndTheHolyGrail", 
                "Hellboy"
            ]
        }, 
        {
            "count": 2, 
            "related_trope": "WomanScorned", 
            "trope": "NonActionGuy", 
            "films": [
                "Futurama", 
                "KillBill"
            ]
        }
    ], 
    "id": "NonActionGuy", 
    "name": "Non Action Guy"
}