{
    "occurrence_over_time": [
        [
            "Films of the 1920s", 
            0, 
            0.0, 
            60
        ], 
        [
            "Films of the 1930s", 
            0, 
            0.0, 
            91
        ], 
        [
            "Films of the 1940s", 
            0, 
            0.0, 
            111
        ], 
        [
            "Films of the 1950s", 
            0, 
            0.0, 
            176
        ], 
        [
            "Films of the 1960s", 
            0, 
            0.0, 
            225
        ], 
        [
            "Films of the 1970s", 
            0, 
            0.0, 
            302
        ], 
        [
            "Films of the 1980s", 
            0, 
            0.0, 
            587
        ], 
        [
            "Films of the 1990s", 
            0, 
            0.0, 
            885
        ], 
        [
            "Films of the 2000s", 
            1, 
            0.0017574692442882249, 
            569
        ], 
        [
            "Films of the 2010s", 
            0, 
            0.0, 
            646
        ]
    ], 
    "description": "In its most literal translation, Onee-sama (also parsed o-nee-sama or oneesama) refers to a highly respected older sister, (which can be troublesome when dubs treat it literally and it isn't). It's an extremely formal phrase, and probably is most commonly heard in period dramas.\nIn modern times, it has three main uses:\n An idol-follower relationship between young women, usually signifying extreme adoration on the part of the follower.\n A subset of the first type of relationship, signalling a lesbian relationship with the uke referring to the seme as \"Onee-sama\". I.e., the Onee-Seme.\n Identification of a very formal and traditional relationship between sisters. Most likely to be used by very traditional families, (miko, samurai, Yamato Nadeshiko, etc.). Tends to be a sign of awe rather than affection. (Awe can mean either adoration, or a type of fear).\nThe Onee-sama is always an older character, if only by a year. She's essentially a princess for the other characters with grace, beauty, and poise. The Onee-sama often overlaps with Aloof Dark-Haired Girl, but usually comes in two flavors.\nOne kind is reflexively affectionate and doting, finding frequent excuses for giving hugs; the kohai is treated like a puppy, although the Onee-sama might be a Dorm Mother.\nThe other is the 'serious' one, a girl who seems cold but enticingly mysterious; almost always the \"alpha\" schoolgirl. As sign that they view themselves as an idol to the rest of their coterie, the Ojou may demand to be referred to this way. When part of a romance she is likely to act possessively towards her object of affection to disguise her romantic feelings.\nMainly appropriated by the yuri fandom, it has become so closely identified with a particular brand of the Sempai Kohai relationship that it is very difficult to use without carrying the connotations of attraction. Ironically, the increasingly overt behavior of Onee-sama can probably also be attributed to shounen's use of this phrase.\nSometimes the term is rejected by its target, because she doesn't want to be the object of adoration and perfection that the term implies. If the romance element is present, a rejection of the term signals that she's straight and so does not return the affections of the girl referring to her as \"Onee-sama\".\nNot to be confused with Oba San.\nContrast with Cool Big Sis, who is less lady-like and more flirty. Often unapologetically so. Due to Values Dissonance, that is where non-Japanese media examples should go as well.", 
    "gender": "f", 
    "adjs": [
        "literal", 
        "formal", 
        "main", 
        "idol-follower", 
        "young"
    ], 
    "adjectives": [
        [
            "onee-sama", 
            2, 
            18.29930014635098, 
            1.0, 
            [
                "OneeSama"
            ]
        ], 
        [
            "formal", 
            2, 
            11.84992150265802, 
            0.647561459066017, 
            [
                "CulturedBadass", 
                "LadyInRed", 
                "YamatoNadeshiko", 
                "KickingAssInAllHerFinery", 
                "QuintessentialBritishGentleman", 
                "PapaWolf", 
                "Samurai", 
                "OneeSama", 
                "Hunk", 
                "Chickification", 
                "Ojou"
            ]
        ], 
        [
            "idol-follower", 
            1, 
            9.14965007317549, 
            0.5, 
            [
                "OneeSama"
            ]
        ], 
        [
            "non-japanese", 
            1, 
            9.14965007317549, 
            0.5, 
            [
                "OneeSama"
            ]
        ], 
        [
            "puppy", 
            1, 
            9.14965007317549, 
            0.5, 
            [
                "OneeSama"
            ]
        ], 
        [
            "traditional", 
            2, 
            8.56178927688526, 
            0.4678752306597117, 
            [
                "YamatoNadeshiko", 
                "HotWitch", 
                "MadScientistsBeautifulDaughter", 
                "TomBoyAndGirlyGirl", 
                "BoyBand", 
                "TomboyPrincess", 
                "Fundoshi", 
                "DoggedNiceGuy", 
                "DistressedDude", 
                "BlondeRepublicanSexKitten", 
                "BeardOfEvil", 
                "OldMaid", 
                "ManInAKilt", 
                "FeminineWomenCanCook", 
                "PassionateSportsGirl", 
                "NaginatasAreFeminine", 
                "CrazyCatLady", 
                "GracefulLadiesLikePurple", 
                "NonActionGuy", 
                "OneeSama", 
                "WomanInWhite", 
                "SweaterGirl", 
                "Fratbro", 
                "SenseiChan", 
                "ThePatriarch", 
                "EvilMatriarch", 
                "HouseWife", 
                "HotGypsyWoman", 
                "DamselOutOfDistress"
            ]
        ], 
        [
            "affectionate", 
            1, 
            8.108327874982516, 
            0.4430949713997329, 
            [
                "ClingyJealousGirl", 
                "OneeSama"
            ]
        ], 
        [
            "lady-like", 
            1, 
            8.108327874982516, 
            0.4430949713997329, 
            [
                "OneeSama", 
                "YamatoNadeshiko"
            ]
        ], 
        [
            "dark-haired", 
            1, 
            6.933736828041756, 
            0.3789072135321195, 
            [
                "LadyOfWar", 
                "BlondesAreEvil", 
                "BlondGuysAreEvil", 
                "OneeSama"
            ]
        ], 
        [
            "present", 
            1, 
            6.5362006463641, 
            0.35718309411234334, 
            [
                "DisappearedDad", 
                "OneeSama", 
                "YamatoNadeshiko", 
                "WickedWitch", 
                "NerdNanny"
            ]
        ], 
        [
            "difficult", 
            1, 
            5.461972042275277, 
            0.2984798324849836, 
            [
                "MachoCamp", 
                "LovelyAngels", 
                "TheLadette", 
                "FavorsForTheSexy", 
                "SexyManInstantHarem", 
                "GracefulLadiesLikePurple", 
                "TroubledButCute", 
                "OneeSama", 
                "ShelteredAristocrat"
            ]
        ], 
        [
            "mysterious", 
            1, 
            4.641601152945787, 
            0.25364910766116694, 
            [
                "MysteriousWaif", 
                "OneeSama", 
                "MysticalWaif", 
                "NerdNanny", 
                "HauntedHeroine", 
                "WinterRoyalLady", 
                "HotWitch", 
                "WomanInBlack", 
                "EmotionlessGirl", 
                "KnightErrant", 
                "WidowWitch"
            ]
        ], 
        [
            "literal", 
            1, 
            4.513342967514272, 
            0.24664019560410713, 
            [
                "TheMuse", 
                "JerkJock", 
                "MachoMasochism", 
                "InnocentFlowerGirl", 
                "PrinceCharmless", 
                "LittleRedFightingHood", 
                "PrinceCharmingWannabe", 
                "BastardBastard", 
                "TheLadette", 
                "OneeSama", 
                "DaddysLittleVillain", 
                "CockFight", 
                "MamaBear", 
                "TheLadysFavour"
            ]
        ], 
        [
            "lesbian", 
            1, 
            4.174900390066524, 
            0.22814535838404898, 
            [
                "ButchLesbian", 
                "LesbianVampire", 
                "TokenLesbian", 
                "PsychoLesbian", 
                "TownGirls", 
                "PassionateSportsGirl", 
                "OneeSama", 
                "LipstickLesbian", 
                "BaitAndSwitchLesbians", 
                "SchoolgirlLesbians", 
                "LesbianJock"
            ]
        ], 
        [
            "particular", 
            1, 
            3.4285033125767717, 
            0.18735707295671858, 
            [
                "WidowWoman", 
                "YamatoNadeshiko", 
                "MamaBear", 
                "WickedStepmother", 
                "AdrenalineMakeover", 
                "BoyBand", 
                "StringyHairedGhostGirl", 
                "ChildSoldiers", 
                "KnightInShiningArmor", 
                "BaitAndSwitchLesbians", 
                "PlayboyBunny", 
                "TakingTheVeil", 
                "PrincessPhase", 
                "Meido", 
                "OneeSama", 
                "JadedWashout", 
                "TheOphelia", 
                "EstrogenBrigade", 
                "GoodOlBoy", 
                "MrFanservice", 
                "SpicyLatina", 
                "VainSorceress", 
                "TheFightingNarcissist", 
                "LittleGirlsKickShins", 
                "MarySue"
            ]
        ], 
        [
            "serious", 
            1, 
            3.1775703743954766, 
            0.17364436612233547, 
            [
                "ChildSoldiers", 
                "DirtyOldMan", 
                "SpaceshipGirl", 
                "BoyBand", 
                "DoggedNiceGuy", 
                "Jailbait", 
                "LipstickAndLoadMontage", 
                "ShamelessFanserviceGirl", 
                "BasementDweller", 
                "GentlemanThief", 
                "Streetwalker", 
                "CrazyJealousGuy", 
                "ChivalrousPervert", 
                "InnocentFanserviceGirl", 
                "Bishonen", 
                "GaussianGirl", 
                "Fangirl", 
                "BaitAndSwitchLesbians", 
                "BromanticFoil", 
                "CuteClumsyGirl", 
                "BrokenBird", 
                "MysteriousWaif", 
                "ReluctantFanserviceGirl", 
                "MysticalWaif", 
                "WomenDrivers", 
                "OneeSama", 
                "LittleMissBadass", 
                "BrawnHilda"
            ]
        ], 
        [
            "straight", 
            1, 
            2.9087699553468287, 
            0.15895525687231593, 
            [
                "YamatoNadeshiko", 
                "MamaBear", 
                "ALadyOnEachArm", 
                "WickedStepmother", 
                "StraightGay", 
                "TheTease", 
                "StandardFiftiesFather", 
                "TheBear", 
                "KnightInShiningArmor", 
                "CampStraight", 
                "TheChiefsDaughter", 
                "MaidenAunt", 
                "MachoCamp", 
                "LesbianCop", 
                "MisplacedKindergartenTeacher", 
                "UselessBoyfriend", 
                "PsychoLesbian", 
                "DecoyDamsel", 
                "QuintessentialBritishGentleman", 
                "OfficeLady", 
                "OneeSama", 
                "EvenTheGirlsWantHer", 
                "BaitAndSwitchLesbians", 
                "TheIngenue", 
                "CrusadingWidower", 
                "HelloNurse", 
                "GayBravado", 
                "GymBunny", 
                "PrinceCharming", 
                "RightThroughHisPants", 
                "DastardlyWhiplash"
            ]
        ], 
        [
            "first", 
            1, 
            2.635414444352818, 
            0.14401722597453212, 
            [
                "AffirmativeActionGirl", 
                "MamaBear", 
                "LawmanGoneBad", 
                "BoyBand", 
                "LadyMacBeth", 
                "MrsClaus", 
                "DoggedNiceGuy", 
                "UnluckyEveryDude", 
                "TheCheerleader", 
                "TheChiefsDaughter", 
                "BashBrothers", 
                "BathingBeauty", 
                "TheFlapper", 
                "MonogenderMonsters", 
                "QuicklyDemotedWoman", 
                "ActionGirl", 
                "PassionateSportsGirl", 
                "DeliberatelyDistressedDamsel", 
                "PrinceCharmless", 
                "MorallyBankruptBanker", 
                "GalleySlave", 
                "InnocentFanserviceGirl", 
                "TheFightingNarcissist", 
                "TroubledButCute", 
                "GaussianGirl", 
                "SensitiveGuyAndManlyMan", 
                "SweetPollyOliver", 
                "HauntedHeroine", 
                "DirtyCoward", 
                "DaddysLittleVillain", 
                "HotScientist", 
                "SenseiChan", 
                "VainSorceress", 
                "GymBunny", 
                "RebelliousPrincess", 
                "KickChick", 
                "OneeSama", 
                "ProperLady", 
                "TestesTest", 
                "PregnantHostage"
            ]
        ], 
        [
            "romantic", 
            1, 
            2.594072712371748, 
            0.14175802853799443, 
            [
                "UnrequitedTragicMaiden", 
                "FemmeFatale", 
                "AdrenalineMakeover", 
                "BastardBoyfriend", 
                "MistressAndServantBoy", 
                "NeutralFemale", 
                "SchoolgirlLesbians", 
                "FinalGirl", 
                "DoggedNiceGuy", 
                "BashBrothers", 
                "LittleSisterHeroine", 
                "MagicalGirlfriend", 
                "NaiveEverygirl", 
                "QuicklyDemotedWoman", 
                "FeminineWomenCanCook", 
                "BespectacledBastardBoyfriend", 
                "TheChanteuse", 
                "InnocentFanserviceGirl", 
                "GaussianGirl", 
                "SensitiveGuyAndManlyMan", 
                "BaitAndSwitchLesbians", 
                "BromanticFoil", 
                "TheIngenue", 
                "CockFight", 
                "UnderstandingBoyfriend", 
                "ButchLesbian", 
                "IllGirl", 
                "SchoolMarm", 
                "Dominatrix", 
                "StumblingUponTheLostWizard", 
                "OneeSama", 
                "AsianHookerStereotype"
            ]
        ], 
        [
            "main", 
            1, 
            1.864169551361889, 
            0.10187108449246451, 
            [
                "SexyStewardess", 
                "MysticalWaif", 
                "MamaBear", 
                "GossipyHens", 
                "TokenLesbian", 
                "SoapBoxSadie", 
                "TheOneGuy", 
                "LovelyAssistant", 
                "TomBoyAndGirlyGirl", 
                "TheCharmer", 
                "CoolBigSis", 
                "MatronChaperone", 
                "Ojou", 
                "GlamorousWartimeSinger", 
                "HandsomeDevil", 
                "MartyStu", 
                "FatGirl", 
                "ShelteredAristocrat", 
                "Joshikousei", 
                "GirlNextDoor", 
                "HardDrinkingPartyGirl", 
                "MaidenAunt", 
                "TheGoodKing", 
                "QuicklyDemotedWoman", 
                "AsianAirhead", 
                "BumblingDad", 
                "UselessBoyfriend", 
                "TheChanteuse", 
                "GrannyClassic", 
                "MountainMan", 
                "InnocentFanserviceGirl", 
                "TheFightingNarcissist", 
                "OneeSama", 
                "SensitiveGuyAndManlyMan", 
                "DirtyCoward", 
                "BromanticFoil", 
                "ActionDad", 
                "Fratbro", 
                "YaoiGuys", 
                "Samurai", 
                "BlackBossLady", 
                "CoolOldLady", 
                "Meido", 
                "Chickification", 
                "TheMuse", 
                "AmazonBrigade", 
                "SexyManInstantHarem", 
                "HookerWithAHeartOfGold", 
                "DeterminedHomesteadersWife", 
                "TheTease"
            ]
        ], 
        [
            "young", 
            1, 
            1.089198295338117, 
            0.05952130882750242, 
            [
                "OverprotectiveDad", 
                "WomanInWhite", 
                "MamaBear", 
                "TheLadette", 
                "GranolaGirl", 
                "PrincelyYoungMan", 
                "BaitAndSwitchLesbians", 
                "LittleRedFightingHood", 
                "DirtyOldMan", 
                "MistressAndServantBoy", 
                "CuteSportsClubManager", 
                "CollegeWidow", 
                "MrsRobinson", 
                "CoolBigSis", 
                "EmotionlessGirl", 
                "MatronChaperone", 
                "SchoolgirlLesbians", 
                "Ojou", 
                "StringyHairedGhostGirl", 
                "GoGetterGirl", 
                "TheSquadette", 
                "NaginatasAreFeminine", 
                "LittleMissAlmighty", 
                "WickedWitch", 
                "MataHari", 
                "NinjaMaid", 
                "SmittenTeenageGirl", 
                "TheHecateSisters", 
                "TheFlapper", 
                "MaidenAunt", 
                "DeterminedWidow", 
                "JeanneDArchetype", 
                "MommasBoy", 
                "GirlsLoveStuffedAnimals", 
                "PirateGirl", 
                "JunglePrincess", 
                "NubileSavage", 
                "BastardGirlfriend", 
                "ShortTank", 
                "OfficeLady", 
                "GrannyClassic", 
                "Kawaiiko", 
                "VainSorceress", 
                "GracefulLadiesLikePurple", 
                "GrandeDame", 
                "BridgeBunnies", 
                "Meido", 
                "EverythingsBetterWithPrincesses", 
                "OneeSama", 
                "Hunk", 
                "GrumpyOldMan", 
                "HotWitch", 
                "TheOphelia", 
                "FilleFatale", 
                "TheWomanWearingTheQueenlyMask", 
                "TheIngenue", 
                "SchoolMarm", 
                "GirlishPigtails", 
                "Fratbro", 
                "MyBelovedSmother", 
                "Tomboy", 
                "SenseiChan", 
                "YaoiGuys", 
                "TinyTyrannicalGirl", 
                "MysteriousWaif", 
                "LesbianVampire", 
                "LeatherMan", 
                "NaiveEverygirl", 
                "PrinceCharming", 
                "BarbaricBully", 
                "MisterSeahorse", 
                "MysticalWaif", 
                "HotScientist", 
                "KidAnova", 
                "PapaWolf", 
                "ShirtlessScene", 
                "ProperLady", 
                "BrawnHilda", 
                "LittleMissBadass", 
                "MagicIdolSinger", 
                "PetitePride", 
                "DarkMagicalGirl", 
                "PluckyGirl", 
                "SexyPriest", 
                "SweetPollyOliver"
            ]
        ]
    ], 
    "image_url": null, 
    "id": "OneeSama", 
    "name": "Onee Sama"
}